heimdall_valid_bank/__init__.py
heimdall_valid_bank/account_validate.py
heimdall_valid_bank/agency_validate.py
heimdall_valid_bank/bank_validate.py
heimdall_valid_bank/base_validate_error.py
heimdall_valid_bank/calculate_number_account.py
heimdall_valid_bank/calculate_number_agency.py
heimdall_valid_bank/common_validate.py
heimdall_valid_bank/data_bank_validate.py
heimdall_valid_bank/generic_validators.py
heimdall_valid_bank/tests/__init__.py
heimdall_valid_bank/tests/data.py
heimdall_valid_bank/tests/test_account_validate.py
heimdall_valid_bank/tests/test_agency_validate.py
heimdall_valid_bank/tests/test_bank_validate.py
heimdall_valid_bank/tests/test_calculate_number_account.py
heimdall_valid_bank/tests/test_calculate_number_agency.py
heimdall_valid_bank/tests/test_data_bank_validate.py
heimdall_valid_bank/utils/__init__.py
heimdall_valid_bank/utils/constants.py
heimdall_valid_bank-1.0.4.dist-info/AUTHORS
heimdall_valid_bank-1.0.4.dist-info/LICENSE
heimdall_valid_bank-1.0.4.dist-info/METADATA
heimdall_valid_bank-1.0.4.dist-info/WHEEL
heimdall_valid_bank-1.0.4.dist-info/top_level.txt
heimdall_valid_bank-1.0.4.dist-info/RECORD
