Metadata-Version: 2.1
Name: heimdall-valid-bank
Version: 1.0.4
Summary: Python implementation for bank account validation.
Home-page: https://github.com/luizalabs/heimdall
Author: Thais Ribeiro
Author-email: thais.ribeiro@luizalabs.com
License: MIT License
Keywords: heimdall,bank,validate
Platform: UNKNOWN
Classifier: Development Status :: 5 - Production/Stable
Classifier: Intended Audience :: Developers
Classifier: License :: OSI Approved :: MIT License
Classifier: Operating System :: OS Independent
Classifier: Programming Language :: Python
Classifier: Programming Language :: Python :: 2
Classifier: Programming Language :: Python :: 2.7
Classifier: Programming Language :: Python :: 3
Classifier: Programming Language :: Python :: 3.6
Classifier: Programming Language :: Python :: 3.7
Classifier: Programming Language :: Python :: 3.8
Requires-Python: >=3
